README.rst
setup.py
currencylayer/__init__.py
currencylayer/client.py
currencylayer/tests.py
currencylayer.egg-info/PKG-INFO
currencylayer.egg-info/SOURCES.txt
currencylayer.egg-info/dependency_links.txt
currencylayer.egg-info/requires.txt
currencylayer.egg-info/top_level.txt