Metadata-Version: 1.1
Name: currencylayer
Version: 0.1
Summary: currencylayer python API client
Home-page: https://github.com/Said007/currencylayer
Author: Said Ali
Author-email: said.ali@msn.com
License: UNKNOWN
Keywords: currency,currencylayer,exchangerate,rates
Platform: UNKNOWN
Classifier: Programming Language :: Python :: 2.7
Classifier: Programming Language :: Python :: 3
Classifier: Programming Language :: Python :: 3.4
Classifier: Programming Language :: Python :: 3.5
